<?xml version='1.0' encoding='UTF-8'?>
<?xml-stylesheet type="text/xsl" href="coswid.xsl"?>
<?xml-model href="coswid.rng" schematypens="http://relaxng.org/ns/structure/1.0" ?>
<registry xmlns="http://www.iana.org/assignments" id="coswid">
  <title>Concise Software Identifier (CoSWID)</title>
  <category>Concise Software Identifier (CoSWID)</category>
  <created>2022-08-01</created>
  <updated>2022-08-01</updated>

  <registry id="coswid-items">
    <title>CoSWID Items</title>  
    <range>
      <value>0-32767</value>
      <registration_rule>Standards Action with Expert Review</registration_rule>
    </range>
    <range>
      <value>32768-4294967295</value>
      <registration_rule>Specification Required</registration_rule>
    </range>
    <xref type="draft" data="RFC-ietf-sacm-coswid-22"/>
    <expert>Unassigned</expert>
    <record date="2022-08-01">
      <value>0</value>
      <name>tag-id</name>
      <xref type="draft" data="RFC-ietf-sacm-coswid-22"/>
    </record>
    <record date="2022-08-01">
      <value>1</value>
      <name>software-name</name>
      <xref type="draft" data="RFC-ietf-sacm-coswid-22"/>
    </record>
    <record date="2022-08-01">
      <value>2</value>
      <name>entity</name>
      <xref type="draft" data="RFC-ietf-sacm-coswid-22"/>
    </record>
    <record date="2022-08-01">
      <value>3</value>
      <name>evidence</name>
      <xref type="draft" data="RFC-ietf-sacm-coswid-22"/>
    </record>
    <record date="2022-08-01">
      <value>4</value>
      <name>link</name>
      <xref type="draft" data="RFC-ietf-sacm-coswid-22"/>
    </record>
    <record date="2022-08-01">
      <value>5</value>
      <name>software-meta</name>
      <xref type="draft" data="RFC-ietf-sacm-coswid-22"/>
    </record>
    <record date="2022-08-01">
      <value>6</value>
      <name>payload</name>
      <xref type="draft" data="RFC-ietf-sacm-coswid-22"/>
    </record>
    <record date="2022-08-01">
      <value>7</value>
      <name>hash</name>
      <xref type="draft" data="RFC-ietf-sacm-coswid-22"/>
    </record>
    <record date="2022-08-01">
      <value>8</value>
      <name>corpus</name>
      <xref type="draft" data="RFC-ietf-sacm-coswid-22"/>
    </record>
    <record date="2022-08-01">
      <value>9</value>
      <name>patch</name>
      <xref type="draft" data="RFC-ietf-sacm-coswid-22"/>
    </record>
    <record date="2022-08-01">
      <value>10</value>
      <name>media</name>
      <xref type="draft" data="RFC-ietf-sacm-coswid-22"/>
    </record>
    <record date="2022-08-01">
      <value>11</value>
      <name>supplemental</name>
      <xref type="draft" data="RFC-ietf-sacm-coswid-22"/>
    </record>
    <record date="2022-08-01">
      <value>12</value>
      <name>tag-version</name>
      <xref type="draft" data="RFC-ietf-sacm-coswid-22"/>
    </record>
    <record date="2022-08-01">
      <value>13</value>
      <name>software-version</name>
      <xref type="draft" data="RFC-ietf-sacm-coswid-22"/>
    </record>
    <record date="2022-08-01">
      <value>14</value>
      <name>version-scheme</name>
      <xref type="draft" data="RFC-ietf-sacm-coswid-22"/>
    </record>
    <record date="2022-08-01">
      <value>15</value>
      <name>lang</name>
      <xref type="draft" data="RFC-ietf-sacm-coswid-22"/>
    </record>
    <record date="2022-08-01">
      <value>16</value>
      <name>directory</name>
      <xref type="draft" data="RFC-ietf-sacm-coswid-22"/>
    </record>
    <record date="2022-08-01">
      <value>17</value>
      <name>file</name>
      <xref type="draft" data="RFC-ietf-sacm-coswid-22"/>
    </record>
    <record date="2022-08-01">
      <value>18</value>
      <name>process</name>
      <xref type="draft" data="RFC-ietf-sacm-coswid-22"/>
    </record>
    <record date="2022-08-01">
      <value>19</value>
      <name>resource</name>
      <xref type="draft" data="RFC-ietf-sacm-coswid-22"/>
    </record>
    <record date="2022-08-01">
      <value>20</value>
      <name>size</name>
      <xref type="draft" data="RFC-ietf-sacm-coswid-22"/>
    </record>
    <record date="2022-08-01">
      <value>21</value>
      <name>file-version</name>
      <xref type="draft" data="RFC-ietf-sacm-coswid-22"/>
    </record>
    <record date="2022-08-01">
      <value>22</value>
      <name>key</name>
      <xref type="draft" data="RFC-ietf-sacm-coswid-22"/>
    </record>
    <record date="2022-08-01">
      <value>23</value>
      <name>location</name>
      <xref type="draft" data="RFC-ietf-sacm-coswid-22"/>
    </record>
    <record date="2022-08-01">
      <value>24</value>
      <name>fs-name</name>
      <xref type="draft" data="RFC-ietf-sacm-coswid-22"/>
    </record>
    <record date="2022-08-01">
      <value>25</value>
      <name>root</name>
      <xref type="draft" data="RFC-ietf-sacm-coswid-22"/>
    </record>
    <record date="2022-08-01">
      <value>26</value>
      <name>path-elements</name>
      <xref type="draft" data="RFC-ietf-sacm-coswid-22"/>
    </record>
    <record date="2022-08-01">
      <value>27</value>
      <name>process-name</name>
      <xref type="draft" data="RFC-ietf-sacm-coswid-22"/>
    </record>
    <record date="2022-08-01">
      <value>28</value>
      <name>pid</name>
      <xref type="draft" data="RFC-ietf-sacm-coswid-22"/>
    </record>
    <record date="2022-08-01">
      <value>29</value>
      <name>type</name>
      <xref type="draft" data="RFC-ietf-sacm-coswid-22"/>
    </record>
    <record>
      <value>30</value>
      <name>Unassigned</name>
    </record>
    <record date="2022-08-01">
      <value>31</value>
      <name>entity-name</name>
      <xref type="draft" data="RFC-ietf-sacm-coswid-22"/>
    </record>
    <record date="2022-08-01">
      <value>32</value>
      <name>reg-id</name>
      <xref type="draft" data="RFC-ietf-sacm-coswid-22"/>
    </record>
    <record date="2022-08-01">
      <value>33</value>
      <name>role</name>
      <xref type="draft" data="RFC-ietf-sacm-coswid-22"/>
    </record>
    <record date="2022-08-01">
      <value>34</value>
      <name>thumbprint</name>
      <xref type="draft" data="RFC-ietf-sacm-coswid-22"/>
    </record>
    <record date="2022-08-01">
      <value>35</value>
      <name>date</name>
      <xref type="draft" data="RFC-ietf-sacm-coswid-22"/>
    </record>
    <record date="2022-08-01">
      <value>36</value>
      <name>device-id</name>
      <xref type="draft" data="RFC-ietf-sacm-coswid-22"/>
    </record>
    <record date="2022-08-01">
      <value>37</value>
      <name>artifact</name>
      <xref type="draft" data="RFC-ietf-sacm-coswid-22"/>
    </record>
    <record date="2022-08-01">
      <value>38</value>
      <name>href</name>
      <xref type="draft" data="RFC-ietf-sacm-coswid-22"/>
    </record><record date="2022-08-01">
      <value>39</value>
      <name>ownership</name>
      <xref type="draft" data="RFC-ietf-sacm-coswid-22"/>
    </record>
    <record date="2022-08-01">
      <value>40</value>
      <name>rel</name>
      <xref type="draft" data="RFC-ietf-sacm-coswid-22"/>
    </record>
    <record date="2022-08-01">
      <value>41</value>
      <name>media-type</name>
      <xref type="draft" data="RFC-ietf-sacm-coswid-22"/>
    </record>
    <record date="2022-08-01">
      <value>42</value>
      <name>use</name>
      <xref type="draft" data="RFC-ietf-sacm-coswid-22"/>
    </record>
    <record date="2022-08-01">
      <value>43</value>
      <name>activation-status</name>
      <xref type="draft" data="RFC-ietf-sacm-coswid-22"/>
    </record>
    <record date="2022-08-01">
      <value>44</value>
      <name>channel-type</name>
      <xref type="draft" data="RFC-ietf-sacm-coswid-22"/>
    </record>
    <record date="2022-08-01">
      <value>45</value>
      <name>colloquial-version</name>
      <xref type="draft" data="RFC-ietf-sacm-coswid-22"/>
    </record>
    <record date="2022-08-01">
      <value>46</value>
      <name>description</name>
      <xref type="draft" data="RFC-ietf-sacm-coswid-22"/>
    </record>
    <record date="2022-08-01">
      <value>47</value>
      <name>edition</name>
      <xref type="draft" data="RFC-ietf-sacm-coswid-22"/>
    </record>
    <record date="2022-08-01">
      <value>48</value>
      <name>entitlement-data-required</name>
      <xref type="draft" data="RFC-ietf-sacm-coswid-22"/>
    </record>
    <record date="2022-08-01">
      <value>49</value>
      <name>entitlement-key</name>
      <xref type="draft" data="RFC-ietf-sacm-coswid-22"/>
    </record>
    <record date="2022-08-01">
      <value>50</value>
      <name>generator</name>
      <xref type="draft" data="RFC-ietf-sacm-coswid-22"/>
    </record>
    <record date="2022-08-01">
      <value>51</value>
      <name>persistent-id</name>
      <xref type="draft" data="RFC-ietf-sacm-coswid-22"/>
    </record>
    <record date="2022-08-01">
      <value>52</value>
      <name>product</name>
      <xref type="draft" data="RFC-ietf-sacm-coswid-22"/>
    </record>
    <record date="2022-08-01">
      <value>53</value>
      <name>product-family</name>
      <xref type="draft" data="RFC-ietf-sacm-coswid-22"/>
    </record>
    <record date="2022-08-01">
      <value>54</value>
      <name>revision</name>
      <xref type="draft" data="RFC-ietf-sacm-coswid-22"/>
    </record>
    <record date="2022-08-01">
      <value>55</value>
      <name>summary</name>
      <xref type="draft" data="RFC-ietf-sacm-coswid-22"/>
    </record>
    <record date="2022-08-01">
      <value>56</value>
      <name>unspsc-code</name>
      <xref type="draft" data="RFC-ietf-sacm-coswid-22"/>
    </record>
    <record date="2022-08-01">
      <value>57</value>
      <name>unspsc-version</name>
      <xref type="draft" data="RFC-ietf-sacm-coswid-22"/>
    </record>
    <record>
      <value>58-4294967295</value>
      <name>Unassigned</name>
    </record>
  </registry>

  <people/>
</registry>
